{"chunk_definitions":[{"row":7,"row_count":1,"visible":true,"expansion_state":0,"options":{"engine":"r","label":"unnamed-chunk-22"},"document_id":"614A2D0C","chunk_id":"cuo7xt0y475gm","chunk_label":"unnamed-chunk-1"},{"row":26,"row_count":1,"visible":true,"expansion_state":0,"options":{"engine":"r","label":"unnamed-chunk-7"},"document_id":"614A2D0C","chunk_id":"cut5jcjwzyh3p","chunk_label":"unnamed-chunk-2"},{"row":61,"row_count":1,"visible":true,"expansion_state":0,"options":{"engine":"r","label":"unnamed-chunk-6"},"document_id":"614A2D0C","chunk_id":"cmi39j78x7fgc","chunk_label":"unnamed-chunk-4"},{"row":67,"row_count":1,"visible":true,"expansion_state":0,"options":{"engine":"r","label":"unnamed-chunk-12"},"document_id":"614A2D0C","chunk_id":"ci9oarbd40h2y","chunk_label":"unnamed-chunk-5"},{"row":87,"row_count":1,"visible":true,"expansion_state":0,"options":{"engine":"r","label":"unnamed-chunk-28"},"document_id":"614A2D0C","chunk_id":"c4cxrqje66ndn","chunk_label":"unnamed-chunk-6"},{"row":95,"row_count":1,"visible":true,"expansion_state":0,"options":{"engine":"r","label":"unnamed-chunk-29"},"document_id":"614A2D0C","chunk_id":"cz5t2dql9eu9h","chunk_label":"unnamed-chunk-7"},{"row":106,"row_count":1,"visible":true,"expansion_state":0,"options":{"engine":"r","label":"unnamed-chunk-25"},"document_id":"614A2D0C","chunk_id":"cjwfgqx32mggt","chunk_label":"unnamed-chunk-8"},{"row":113,"row_count":1,"visible":true,"expansion_state":0,"options":{"engine":"r","label":"unnamed-chunk-27"},"document_id":"614A2D0C","chunk_id":"c0agju6j3uwv7","chunk_label":"unnamed-chunk-9"}],"doc_write_time":1618352137}